dep_mongo/__init__.py
pyproject.toml
dep_module_mongo-2.13.29.dist-info/WHEEL
dep_module_mongo-2.13.29.dist-info/METADATA
dep_module_mongo-2.13.29.dist-info/RECORD
