Metadata-Version: 2.1
Name: dep-module-mongo
Version: 2.13.29
Summary: 
Author: everhide
Author-email: i.tolkachnikov@gmail.com
Requires-Python: >=3.9,<=3.11
Classifier: Programming Language :: Python :: 3
Classifier: Programming Language :: Python :: 3.10
Classifier: Programming Language :: Python :: 3.9
Requires-Dist: beanie (>=1.11.9,<2.0.0)
Requires-Dist: dep-spec (>=2.3.29,<3.0.0)
Requires-Dist: poetry (==1.1.15)
